docassemble/ALAffidavitOfIndigency/__init__.py
docassemble/ALAffidavitOfIndigency/data/questions/affidavit.yml
docassemble/ALAffidavitOfIndigency/data/questions/affidavit_body.yml
docassemble/ALAffidavitOfIndigency/data/questions/affidavit_of_indigency_supplement_body.yml
docassemble/ALAffidavitOfIndigency/data/questions/review_page.yml
docassemble/ALAffidavitOfIndigency/data/sources/README.md
docassemble/ALAffidavitOfIndigency/data/sources/all_through.feature
docassemble/ALAffidavitOfIndigency/data/static/README.md
docassemble/ALAffidavitOfIndigency/data/templates/README.md
docassemble/ALAffidavitOfIndigency/data/templates/affidavit_of_indigency_supplement.pdf
docassemble/ALAffidavitOfIndigency/data/templates/affidavit_of_indigency_supplement_next_steps.docx
docassemble/ALAffidavitOfIndigency/data/templates/affidavitofindigency.pdf
docassemble_alaffidavitofindigency-2.2.0.dist-info/licenses/LICENSE
docassemble_alaffidavitofindigency-2.2.0.dist-info/METADATA
docassemble_alaffidavitofindigency-2.2.0.dist-info/WHEEL
docassemble_alaffidavitofindigency-2.2.0.dist-info/top_level.txt
docassemble_alaffidavitofindigency-2.2.0.dist-info/RECORD
