Metadata-Version: 2.4
Name: docassemble.ALAffidavitOfIndigency
Version: 2.2.0
Summary: The Massachusetts Affidavit of Indigency, or Fee waiver form
Home-page: https://courtformsonline.org
Author: Suffolk LIT Lab
Author-email: litlab@suffolk.edu
License: The MIT License (MIT)
License-File: LICENSE
Requires-Dist: docassemble.AssemblyLine
Requires-Dist: docassemble.MassAccess
Requires-Dist: docassemble.PovertyScale
Requires-Dist: docassemble.ALToolbox>=0.7.1
Requires-Dist: docassemble.ALMassachusetts>=0.2.0
Requires-Dist: docassemble.GithubFeedbackForm>=0.2.1
Dynamic: author
Dynamic: author-email
Dynamic: description
Dynamic: description-content-type
Dynamic: home-page
Dynamic: license
Dynamic: license-file
Dynamic: requires-dist
Dynamic: summary
